{"Map":{
"亘":["ɤn˨"],
"房":["fɑŋ"],
"份":["fən"],
"分":["fən"],
"逢":["fɤŋ"],
"菲":["fɪ˨"],
"傅":["fu˨"],
"孚":["fu˨"],
"抚":["fu˨"],
"甫":["fu˨"],
"压":["ia˥"],
"愉":["iu˨"],
"殷":["ɪn˨"],
"淫":["ɪn˨"],
"价":["jɑ˥"],
"夹":["jɑ˥"],
"钾":["jɑ˥"],
"捷":["jɛ˥"],
"秸":["jɛ˥"],
"节":["jɛ˥"],
"芥":["jɛ˥"],
"解":["jɛ˥"],
"睫":["jɛ˧"],
"居":["jɤ˨"],
"洁":["jɤ˨"],
"籍":["jɤ˨"],
"纠":["jɤ˨"],
"结":["jɤ˨"],
"觉":["jɤ˨"],
"激":["ji˥"],
"髻":["ji˥"],
"几":["ji˨"],
"给":["ji˨"],
"祭":["jɪ˥"],
"肌":["jɪ˥"],
"藉":["jɪ˥"],
"脊":["jɪ˨"],
"脚":["jɔ˨"],
"究":["jy˨"],
"喀":["kɑ˥"],
"看":["kɑ˥"],
"跨":["kɑ˥"],
"疴":["kɤ˨"],
"磕":["kɤ˨"],
"苛":["kɤ˨"],
"颗":["kɤ˨"],
"棵":["kɔ˥"],
"科":["kɔ˨"],
"腊":["la˥"],
"勒":["lɤ˨"],
"隶":["li˨"],
"罗":["lɔ˥"],
"络":["lɔ˨"],
"路":["lu˨"],
"陆":["lu˨"],
"鹿":["lu˨"],
"吗":["ma˨"],
"谜":["mi˥"],
"秘":["mi˨"],
"糜":["mi˨"],
"迷":["mi˨"],
"靡":["mi˨"],
"模":["mo˨"],
"磨":["mo˨"],
"膜":["mɔ˥"],
"摩":["mɔ˨"],
"摸":["mɔ˨"],
"莫":["mɔ˨"],
"嫩":["nɤ˧"],
"妮":["ni˧"],
"泥":["ni˨"],
"溺":["ni˨"],
"黏":["ni˨"],
"弄":["nɔ˥"],
"欧":["ou˨"],
"帕":["pa˥"],
"扒":["pa˨"],
"派":["pɑ˨"],
"扁":["pɛ˥"],
"边":["pi˧"],
"便":["pi˨"],
"片":["pi˨"],
"咯":["ɻɔ˨"],
"锯":["ɻu˨"],
"撒":["sa˨"],
"洒":["sa˨"],
"射":["ʂɤ˨"],
"涉":["ʂɤ˨"],
"舌":["ʂɤ˨"],
"属":["ʂu˨"],
"术":["ʂu˨"],
"蔬":["ʂu˨"],
"熟":["ʂʊ˨"],
"拓":["tɑ˥"],
"陀":["tɑ˥"],
"梯":["tɪ˥"],
"踢":["tɪ˥"],
"蹄":["tɪ˥"],
"尺":["ʈʂʰ"],
"吁":["ɥo˨"],
"瓦":["wa˥"],
"汶":["wən"],
"温":["wən"],
"瘟":["wən"],
"闻":["wən"],
"魏":["wɛ˨"],
"为":["wɤ˨"],
"乌":["wɤ˨"],
"委":["wɤ˨"],
"畏":["wɤ˨"],
"倭":["wɔ˨"],
"涡":["wɔ˨"],
"钨":["wɔ˨"],
"吓":["xa˥"],
"偕":["xe˧"],
"穴":["xe˨"],
"喝":["xɤ˨"],
"携":["xi˧"],
"戏":["xi˨"],
"洽":["xi˨"],
"溪":["xi˨"],
"熄":["xi˨"],
"系":["xi˨"],
"胥":["xu˨"],
"虚":["xu˨"],
"许":["xu˨"],
"需":["xu˨"],
"遗":["yi˨"],
"予":["yu˨"],
"辙":["ʐɤ˨"],
"哈":["˥ɑ"],
"耶":["˥ɛ"],
"尾":["˥ʊ"],
"胺":["a˨"],
"阿":["a˨"],
"盐":["ɑ˥"],
"罕":["ɑ˥"],
"阎":["ɑ˥"],
"椎":["ɕʐ"],
"赐":["ɕʐ"],
"蛾":["e˥"],
"诶":["e˥"],
"恶":["ɛ˥"],
"耳":["ɚ˨"],
"溘":["ɤ˨"],
"夫":["fɤ"],
"椅":["i˥"],
"依":["i˨"],
"咽":["i˨"],
"壹":["i˨"],
"揖":["i˨"],
"液":["i˨"],
"燕":["i˨"],
"移":["i˨"],
"臆":["i˨"],
"衣":["i˨"],
"谊":["i˨"],
"迟":["i˨"],
"阴":["i˨"],
"鞅":["i˨"],
"弛":["ɪ˥"],
"迦":["ɪ˨"],
"假":["j˨"],
"拘":["jɤ"],
"可":["kɤ"],
"能":["ŋ˥"],
"喔":["ɔ˥"],
"奧":["ɔ˨"],
"过":["ɔ˨"],
"裴":["pɤ"],
"杀":["ʂa"],
"於":["u˨"],
"疟":["ɥɤ"],
"危":["wɤ"],
"与":["y˨"],
"于":["y˨"],
"余":["y˨"],
"喻":["y˨"],
"涌":["y˨"],
"语":["y˨"],
"豫":["y˨"],
"逾":["y˨"],
"雨":["y˨"],
"儿":["ɚ"],
"而":["ɚ"],
"鞥":["ɤ"],
"什":["ʂ"],
"㮮":["tɕjɛ˧˥_"],
"䩩":["ɥœn˨˩˦_"],
"䩮":["lu˥˩_"],
"婩":["jɛn˥˩_"],
"宩":["ʂɚ˨˩˦_"],
"橩":["tɕʰjʊŋ˧˥_"],
"橮":["ljoʊ˨˩˦_"],
"殩":["tsʰwan˥˩_"],
"穮":["pjɑʊ˥˥_"],
"箩":["luɔ˧˥_"],
"驮":["tuɔ˥˩"],
"":[]},
"SrcMulti":null,"DstMulti":null,"SrcMultiSuffix":null,"DstMultiSuffix":null,"DropLast":null,"DstMultiPrefix":null,"PrePhonWordSteps":[{"Normalize":"NFC"}],
"SplitBefore":["《","（","(","·","“"],
"SplitAfter":["》","）",")","。","？","、","，","：","、","；","！","?","!",".","”"],
"IsDuplex":false,"IsSrcSurround":false}
